{
  "id": "listening-a2-031",
  "level": "A2",
  "title": "At the Sports Club",
  "summary": "A new member joins a sports club and speaks with the coach about training schedules, equipment, and her fitness goals.",
  "format": "dialogue",
  "body": [
    {
      "speaker": "Member",
      "text": "Hi, I just joined the club last week. I'm not sure where to start."
    },
    {
      "speaker": "Coach",
      "text": "Welcome! My name's David. I'm the head coach here. What's your name?"
    },
    {
      "speaker": "Member",
      "text": "I'm Lisa. I've never really trained at a sports club before, so I'm a bit nervous."
    },
    {
      "speaker": "Coach",
      "text": "Don't worry, everyone feels that way at the beginning. What sport are you interested in?"
    },
    {
      "speaker": "Member",
      "text": "I'd like to try swimming and maybe some gym work. I want to get fitter."
    },
    {
      "speaker": "Coach",
      "text": "That's a great combination. The pool is open from six in the morning until nine at night."
    },
    {
      "speaker": "Member",
      "text": "That's good. Do I need to book a lane, or can I just turn up?"
    },
    {
      "speaker": "Coach",
      "text": "For the pool, you can just turn up on weekdays. At weekends, it's better to book in advance because it gets quite busy."
    },
    {
      "speaker": "Member",
      "text": "OK, I'll keep that in mind. What about the gym? Is there an induction session?"
    },
    {
      "speaker": "Coach",
      "text": "Yes, all new members must complete an induction before using the gym equipment. I can book you in for one this Thursday at five o'clock."
    },
    {
      "speaker": "Member",
      "text": "Thursday at five works perfectly for me. Do I need to bring anything?"
    },
    {
      "speaker": "Coach",
      "text": "Just wear comfortable sports clothes and bring a water bottle. Trainers are essential — no bare feet in the gym."
    },
    {
      "speaker": "Member",
      "text": "Of course. How long does the induction take?"
    },
    {
      "speaker": "Coach",
      "text": "About an hour. We'll go through all the machines and I'll help you set some personal goals."
    },
    {
      "speaker": "Member",
      "text": "That sounds really helpful. Thank you so much, David."
    },
    {
      "speaker": "Coach",
      "text": "My pleasure. See you on Thursday, and enjoy your first swim!"
    }
  ],
  "tags": [
    "sports",
    "fitness",
    "everyday life"
  ],
  "annotations": [
    {
      "phrase": "head coach",
      "meaningVi": "huấn luyện viên trưởng",
      "pronunciation": "/hed kəʊtʃ/",
      "exampleEn": "She is the head coach of the national swimming team."
    },
    {
      "phrase": "a bit nervous",
      "meaningVi": "hơi lo lắng / hơi hồi hộp",
      "pronunciation": "/ə bɪt ˈnɜːvəs/",
      "exampleEn": "I'm a bit nervous about the exam tomorrow."
    },
    {
      "phrase": "great combination",
      "meaningVi": "sự kết hợp tuyệt vời",
      "pronunciation": "/ɡreɪt ˌkɒmbɪˈneɪʃən/",
      "exampleEn": "Running and yoga is a great combination for fitness."
    },
    {
      "phrase": "book a lane",
      "meaningVi": "đặt trước một làn bơi",
      "pronunciation": "/bʊk ə leɪn/",
      "exampleEn": "You need to book a lane at the pool for Saturday morning."
    },
    {
      "phrase": "turn up",
      "meaningVi": "xuất hiện / đến (mà không báo trước)",
      "pronunciation": "/tɜːn ʌp/",
      "exampleEn": "You don't need a reservation — just turn up."
    },
    {
      "phrase": "book in advance",
      "meaningVi": "đặt trước",
      "pronunciation": "/bʊk ɪn ədˈvɑːns/",
      "exampleEn": "I always book a table in advance at busy restaurants."
    },
    {
      "phrase": "keep that in mind",
      "meaningVi": "ghi nhớ điều đó",
      "pronunciation": "/kiːp ðæt ɪn maɪnd/",
      "exampleEn": "Prices may change — keep that in mind when you plan your budget."
    },
    {
      "phrase": "induction session",
      "meaningVi": "buổi hướng dẫn nhập môn",
      "pronunciation": "/ɪnˈdʌkʃən ˈseʃən/",
      "exampleEn": "New staff must attend an induction session on their first day."
    },
    {
      "phrase": "gym equipment",
      "meaningVi": "thiết bị phòng tập",
      "pronunciation": "/dʒɪm ɪˈkwɪpmənt/",
      "exampleEn": "Please wipe down the gym equipment after use."
    },
    {
      "phrase": "trainers are essential",
      "meaningVi": "giày thể thao là bắt buộc",
      "pronunciation": "/ˈtreɪnəz ər ɪˈsenʃəl/",
      "exampleEn": "Trainers are essential for any gym session."
    },
    {
      "phrase": "personal goals",
      "meaningVi": "mục tiêu cá nhân",
      "pronunciation": "/ˈpɜːsənəl ɡəʊlz/",
      "exampleEn": "The trainer helped me set personal goals for the next three months."
    },
    {
      "phrase": "my pleasure",
      "meaningVi": "rất vui được giúp bạn (đáp lại lời cảm ơn)",
      "pronunciation": "/maɪ ˈpleʒə/",
      "exampleEn": "'Thank you for your help.' 'My pleasure!'"
    }
  ],
  "grammarNotes": [
    {
      "title": "Modal verb 'must' for obligation: 'All new members must complete an induction'",
      "bodyVi": "'Must + verb nguyên thể' diễn tả sự bắt buộc — điều gì đó là cần thiết và không thể bỏ qua. 'All new members must complete an induction before using the gym equipment.' Đây là quy định của câu lạc bộ. So sánh: 'must' (bắt buộc, từ quy tắc hoặc người nói) và 'have to' (bắt buộc từ hoàn cảnh bên ngoài). Trong ngữ cảnh chính thức như quy định của câu lạc bộ, 'must' rất phổ biến.",
      "bodyEn": "Use 'must + bare infinitive' to express obligation — something is required and cannot be skipped. Example: 'All new members must complete an induction.' This is a club rule. 'Must' often expresses internal or institutional obligation. Compare: 'You must wear trainers' (rule) vs 'You have to wear trainers' (external requirement). Both are acceptable here, but 'must' is common in formal rules and signs."
    },
    {
      "title": "'I'd like to' for polite requests and wishes",
      "bodyVi": "'I'd like to + verb nguyên thể' là cách lịch sự và tự nhiên để diễn tả mong muốn hoặc yêu cầu. 'I'd like to try swimming' — Tôi muốn thử bơi lội. Đây lịch sự hơn 'I want to try swimming.' Bạn cũng có thể dùng 'I'd like to book an induction' khi yêu cầu dịch vụ. Đây là một trong những cách diễn đạt quan trọng nhất trong giao tiếp hàng ngày.",
      "bodyEn": "Use 'I'd like to + bare infinitive' for polite wishes or requests. It is more formal and polite than 'I want to.' Examples: 'I'd like to try swimming.' / 'I'd like to book a session.' In service interactions (shops, sports clubs, restaurants), 'I'd like to' is the standard polite form. You can also offer: 'Would you like to...?' for suggestions."
    }
  ],
  "translationVi": "Thành viên: Xin chào, tôi vừa tham gia câu lạc bộ tuần trước. Tôi không biết bắt đầu từ đâu.\nHuấn luyện viên: Chào mừng! Tôi tên David. Tôi là huấn luyện viên trưởng ở đây. Bạn tên gì?\nThành viên: Tôi là Lisa. Tôi chưa bao giờ tập luyện tại câu lạc bộ thể thao trước đây, nên tôi hơi lo lắng.\nHuấn luyện viên: Đừng lo, ai cũng cảm thấy vậy lúc đầu. Bạn quan tâm đến môn thể thao nào?\nThành viên: Tôi muốn thử bơi lội và có thể tập gym. Tôi muốn rèn luyện sức khỏe.\nHuấn luyện viên: Đó là sự kết hợp tuyệt vời. Hồ bơi mở cửa từ sáu giờ sáng đến chín giờ tối.\nThành viên: Tốt quá. Tôi có cần đặt trước một làn bơi không, hay có thể đến trực tiếp?\nHuấn luyện viên: Đối với hồ bơi, bạn có thể đến thẳng vào các ngày trong tuần. Vào cuối tuần thì nên đặt trước vì khá đông.\nThành viên: OK, tôi sẽ ghi nhớ điều đó. Còn phòng gym thì sao? Có buổi hướng dẫn nhập môn không?\nHuấn luyện viên: Có, tất cả thành viên mới phải hoàn thành buổi hướng dẫn trước khi sử dụng thiết bị phòng gym. Tôi có thể đặt lịch cho bạn vào thứ Năm này lúc năm giờ.\nThành viên: Thứ Năm lúc năm giờ hoàn toàn phù hợp với tôi. Tôi có cần mang theo gì không?\nHuấn luyện viên: Chỉ cần mặc quần áo thể thao thoải mái và mang theo bình nước. Giày thể thao là bắt buộc — không được đi chân trần trong phòng gym.\nThành viên: Tất nhiên rồi. Buổi hướng dẫn mất bao lâu?\nHuấn luyện viên: Khoảng một tiếng. Chúng ta sẽ tìm hiểu tất cả các máy và tôi sẽ giúp bạn đặt ra mục tiêu cá nhân.\nThành viên: Nghe thật hữu ích. Cảm ơn bạn rất nhiều, David.\nHuấn luyện viên: Rất vui được giúp. Hẹn gặp bạn vào thứ Năm, và chúc bạn có buổi bơi đầu tiên vui vẻ!",
  "questions": [
    {
      "id": "q1",
      "prompt": "When did Lisa join the sports club?",
      "options": [
        "Yesterday",
        "Last week",
        "Last month",
        "Today"
      ],
      "answerIndex": 1,
      "explanation": "Lisa says 'I just joined the club last week.'",
      "hint": "She mentions the exact time in her first sentence."
    },
    {
      "id": "q2",
      "prompt": "What is the coach's name?",
      "options": [
        "Daniel",
        "Derek",
        "David",
        "Duncan"
      ],
      "answerIndex": 2,
      "explanation": "The coach says 'My name's David.'",
      "hint": "He introduces himself immediately."
    },
    {
      "id": "q3",
      "prompt": "Which two activities does Lisa want to try?",
      "options": [
        "Tennis and running",
        "Swimming and gym work",
        "Cycling and yoga",
        "Basketball and swimming"
      ],
      "answerIndex": 1,
      "explanation": "'I'd like to try swimming and maybe some gym work.'",
      "hint": "She mentions a water sport and exercise indoors."
    },
    {
      "id": "q4",
      "prompt": "What time does the pool open?",
      "options": [
        "Seven in the morning",
        "Eight in the morning",
        "Six in the morning",
        "Five in the morning"
      ],
      "answerIndex": 2,
      "explanation": "'The pool is open from six in the morning until nine at night.'",
      "hint": "The opening time is early."
    },
    {
      "id": "q5",
      "prompt": "When does Lisa need to book a lane in advance?",
      "options": [
        "Every day",
        "Only on Mondays",
        "On weekdays",
        "At weekends"
      ],
      "answerIndex": 3,
      "explanation": "'At weekends, it's better to book in advance because it gets quite busy.'",
      "hint": "On weekdays you can just turn up."
    },
    {
      "id": "q6",
      "prompt": "What must all new members do before using the gym?",
      "options": [
        "Pay an extra fee",
        "Complete an induction session",
        "Get a doctor's certificate",
        "Watch a safety video"
      ],
      "answerIndex": 1,
      "explanation": "'All new members must complete an induction before using the gym equipment.'",
      "hint": "It is a requirement, not optional."
    },
    {
      "id": "q7",
      "prompt": "When is Lisa's induction session booked for?",
      "options": [
        "Wednesday at five",
        "Thursday at four",
        "Thursday at five",
        "Friday at five"
      ],
      "answerIndex": 2,
      "explanation": "'I can book you in for one this Thursday at five o'clock.'",
      "hint": "The day and time are both mentioned."
    },
    {
      "id": "q8",
      "prompt": "What does the coach say Lisa must bring to the induction?",
      "options": [
        "Sports clothes and a water bottle",
        "A towel and goggles",
        "Her membership card and ID",
        "A sports bag and gloves"
      ],
      "answerIndex": 0,
      "explanation": "'Just wear comfortable sports clothes and bring a water bottle.'",
      "hint": "Two items are mentioned."
    },
    {
      "id": "q9",
      "prompt": "What footwear rule does the coach mention?",
      "options": [
        "Flip-flops are required",
        "Any shoes are acceptable",
        "Trainers are essential — no bare feet",
        "Trainers must be new"
      ],
      "answerIndex": 2,
      "explanation": "'Trainers are essential — no bare feet in the gym.'",
      "hint": "He gives a specific reason for the rule."
    },
    {
      "id": "q10",
      "prompt": "How long does the induction session take?",
      "options": [
        "Thirty minutes",
        "Forty-five minutes",
        "About an hour",
        "Two hours"
      ],
      "answerIndex": 2,
      "explanation": "'About an hour.'",
      "hint": "The coach gives an approximate duration."
    },
    {
      "id": "q11",
      "prompt": "What will the coach help Lisa do during the induction?",
      "options": [
        "Sign up for a swimming class",
        "Set some personal goals",
        "Meet other members",
        "Choose a training plan"
      ],
      "answerIndex": 1,
      "explanation": "'I'll help you set some personal goals.'",
      "hint": "This is about Lisa's own fitness ambitions."
    },
    {
      "id": "q12",
      "prompt": "Why does Lisa say she is nervous?",
      "options": [
        "She is not a good swimmer",
        "She does not know the coach",
        "She has never trained at a sports club before",
        "She is afraid of the gym equipment"
      ],
      "answerIndex": 2,
      "explanation": "'I've never really trained at a sports club before, so I'm a bit nervous.'",
      "hint": "She explains the reason directly."
    }
  ],
  "cloze": {
    "template": "Member: Hi, I just {{b1}} the club last week. I'm not sure where to start.\nCoach: Welcome! My name's David. I'm the head {{b2}} here. What's your name?\nMember: I'm Lisa. I've never really trained at a sports club before, so I'm a bit nervous.\nCoach: Don't worry, everyone feels that way at the beginning. What sport are you {{b3}} in?\nMember: I'd like to try swimming and maybe some gym work. I want to get {{b4}}.\nCoach: That's a great combination. The pool is open from six in the morning until nine at {{b5}}.\nMember: That's good. Do I need to book a lane, or can I just turn up?\nCoach: For the pool, you can just turn up on weekdays. At weekends, it's better to book in {{b6}} because it gets quite busy.\nMember: OK, I'll keep that in mind. What about the gym? Is there an {{b7}} session?\nCoach: Yes, all new members must complete an induction before using the gym {{b8}}. I can book you in for one this Thursday at five o'clock.\nMember: Thursday at five works perfectly for me. Do I need to bring anything?\nCoach: Just wear comfortable sports clothes and bring a water {{b9}}. Trainers are essential — no bare feet in the gym.\nMember: Of course. How long does the induction take?\nCoach: About an {{b10}}. We'll go through all the machines and I'll help you set some personal goals.",
    "blanks": [
      {
        "id": "b1",
        "options": [
          "found",
          "entered",
          "joined",
          "visited"
        ],
        "answerIndex": 2,
        "explanation": "'joined' — you join a club when you become a member."
      },
      {
        "id": "b2",
        "options": [
          "trainer",
          "instructor",
          "coach",
          "manager"
        ],
        "answerIndex": 2,
        "explanation": "'coach' — he is introduced as the head coach."
      },
      {
        "id": "b3",
        "options": [
          "good",
          "interested",
          "experienced",
          "skilled"
        ],
        "answerIndex": 1,
        "explanation": "'interested' — 'interested in' is the correct collocation for hobbies and topics."
      },
      {
        "id": "b4",
        "options": [
          "stronger",
          "healthier",
          "fitter",
          "better"
        ],
        "answerIndex": 2,
        "explanation": "'fitter' — the passage says 'I want to get fitter.'"
      },
      {
        "id": "b5",
        "options": [
          "midnight",
          "evening",
          "night",
          "dusk"
        ],
        "answerIndex": 2,
        "explanation": "'night' — the pool is open 'until nine at night.'"
      },
      {
        "id": "b6",
        "options": [
          "time",
          "advance",
          "front",
          "early"
        ],
        "answerIndex": 1,
        "explanation": "'advance' — 'book in advance' means to reserve something before you need it."
      },
      {
        "id": "b7",
        "options": [
          "introduction",
          "induction",
          "orientation",
          "welcome"
        ],
        "answerIndex": 1,
        "explanation": "'induction' — an induction session is required for new gym members."
      },
      {
        "id": "b8",
        "options": [
          "machines",
          "area",
          "equipment",
          "facilities"
        ],
        "answerIndex": 2,
        "explanation": "'equipment' — 'gym equipment' refers to all machines and tools in the gym."
      },
      {
        "id": "b9",
        "options": [
          "bag",
          "cup",
          "bottle",
          "flask"
        ],
        "answerIndex": 2,
        "explanation": "'bottle' — 'water bottle' is the standard expression."
      },
      {
        "id": "b10",
        "options": [
          "session",
          "hour",
          "day",
          "class"
        ],
        "answerIndex": 1,
        "explanation": "'hour' — 'about an hour' gives the approximate duration."
      }
    ]
  },
  "criticalThinkingQuestion": "Lisa says she wants to get fitter and has chosen swimming and gym work. What do you think are the best types of exercise for someone who is just starting out, and what advice would you give to a complete beginner at a sports club?",
  "accents": [
    "en-US",
    "en-GB"
  ],
  "voices": {
    "Member": {
      "sex": "female",
      "age": "adult",
      "accent": "en-US",
      "edgeVoice": "en-US-AvaNeural"
    },
    "Coach": {
      "sex": "male",
      "age": "adult",
      "accent": "en-GB",
      "edgeVoice": "en-GB-ThomasNeural"
    }
  },
  "sentences": [
    {
      "id": "s1",
      "speaker": "Member",
      "text": "Hi, I just joined the club last week.",
      "durationMs": 2448
    },
    {
      "id": "s2",
      "speaker": "Member",
      "text": "I'm not sure where to start.",
      "durationMs": 1848
    },
    {
      "id": "s3",
      "speaker": "Coach",
      "text": "Welcome! My name's David.",
      "durationMs": 3480
    },
    {
      "id": "s4",
      "speaker": "Coach",
      "text": "I'm the head coach here. What's your name?",
      "durationMs": 3984
    },
    {
      "id": "s5",
      "speaker": "Member",
      "text": "I'm Lisa. I've never really trained at a sports club before, so I'm a bit nervous.",
      "durationMs": 5640
    },
    {
      "id": "s6",
      "speaker": "Coach",
      "text": "Don't worry, everyone feels that way at the beginning. What sport are you interested in?",
      "durationMs": 6192
    },
    {
      "id": "s7",
      "speaker": "Member",
      "text": "I'd like to try swimming and maybe some gym work. I want to get fitter.",
      "durationMs": 4728
    },
    {
      "id": "s8",
      "speaker": "Coach",
      "text": "That's a great combination. The pool is open from six in the morning until nine at night.",
      "durationMs": 6408
    },
    {
      "id": "s9",
      "speaker": "Member",
      "text": "That's good. Do I need to book a lane, or can I just turn up?",
      "durationMs": 3888
    },
    {
      "id": "s10",
      "speaker": "Coach",
      "text": "For the pool, you can just turn up on weekdays. At weekends, it's better to book in advance because it gets quite busy.",
      "durationMs": 8064
    },
    {
      "id": "s11",
      "speaker": "Member",
      "text": "OK, I'll keep that in mind. What about the gym? Is there an induction session?",
      "durationMs": 5280
    },
    {
      "id": "s12",
      "speaker": "Coach",
      "text": "Yes, all new members must complete an induction before using the gym equipment. I can book you in for one this Thursday at five o'clock.",
      "durationMs": 8880
    },
    {
      "id": "s13",
      "speaker": "Member",
      "text": "Thursday at five works perfectly for me. Do I need to bring anything?",
      "durationMs": 4488
    },
    {
      "id": "s14",
      "speaker": "Coach",
      "text": "Just wear comfortable sports clothes and bring a water bottle. Trainers are essential — no bare feet in the gym.",
      "durationMs": 7608
    },
    {
      "id": "s15",
      "speaker": "Member",
      "text": "Of course. How long does the induction take?",
      "durationMs": 3144
    },
    {
      "id": "s16",
      "speaker": "Coach",
      "text": "About an hour. We'll go through all the machines and I'll help you set some personal goals.",
      "durationMs": 6432
    },
    {
      "id": "s17",
      "speaker": "Member",
      "text": "That sounds really helpful. Thank you so much, David.",
      "durationMs": 3936
    },
    {
      "id": "s18",
      "speaker": "Coach",
      "text": "My pleasure. See you on Thursday, and enjoy your first swim!",
      "durationMs": 5376
    }
  ],
  "audio": {
    "cdnBase": "https://cdn.jsdelivr.net/gh/thanhphongdo/english-learning-audio@main/listening-a2-031",
    "manifestVersion": 1
  },
  "totalDurationMs": 91824
}
