{
  "id": "reading-c1-051",
  "level": "C1",
  "title": "Read back",
  "summary": "An essay on the quiet authority of the court stenographer: not the recording of words as they are spoken, but the strange transformation that takes place the moment the transcript is read aloud, into a record that the room now agrees was what was said.",
  "format": "paragraph",
  "body": "Most people imagine a stenographer as a kind of stenographic camera — a person taking down what is said because the law requires a record, and faithful in proportion to her speed. It is a misunderstanding, but a useful one. It is the misunderstanding that lets the room continue. What is in fact happening at the small machine by the witness box is closer to a quiet act of authorship, one that few participants in a courtroom understand, and which the stenographer herself, if she is honest, will not entirely defend.\n\nThe machine records phonemes, not sentences. The reporter is interpreting in real time — collapsing 'uh's, supplying punctuation she did not hear, deciding where a question ends and a clarification begins. Two stenographers, working from identical audio, will produce transcripts that differ in roughly two per cent of their content; the differences are almost never in the words but in the breath marks between them, and breath marks decide where a sentence stops being one thing and starts being another. This is not a failure of the profession. It is the profession.\n\nThe interesting moment, however, is not the recording. It is the reading back. When counsel asks 'could you read back the witness's last answer', what is produced is no longer a recording at all. It is a text. And the moment that text is read aloud in the witness's hearing, something happens that nobody in the room quite acknowledges: the witness ratifies it. She nods, or she corrects a word, or she sits silent, but in each case the transcript becomes — by the slender mechanism of her not contradicting it — what was said. The reading back is the act that closes the question. After it, what the room remembers is no longer the testimony but the transcript of the testimony, and the two have, by then, parted company in small and binding ways.\n\nI have read back testimony for thirty-one years, in three jurisdictions, in two languages. The thing I have learned, which I would not have predicted at the start, is that the read-back is the most consequential moment of any trial that is not the verdict. A witness who is allowed to hear her words returned to her in cool, ordered prose — punctuation supplied, hesitations filed away — will, more often than not, settle for that version. It sounds more like what she meant than what she actually said. The honest mess of speech is replaced, with her consent, by a tidier proxy. And the tidier proxy is what the appeal court will read, twenty months later, in a room she will never see.\n\nThere are stenographers who are uneasy about this and stenographers who are not. I have been both at different points in my career. The uneasy version of me kept a private log, for several years, of moments where the read-back, in my own judgement, departed materially from the testimony. The log was short. It contained fewer than forty entries in twelve years. But the entries had a pattern: they almost always involved witnesses for whom English was a second language, witnesses who had been crying, witnesses under cross-examination by counsel skilled at pressing for cleaner sentences than the witness was capable of. The read-back, in those instances, tidied them. They accepted the tidying. The court accepted their acceptance.\n\nI no longer keep the log. The reason is not that I have stopped noticing, but that I came to believe the log was its own quiet self-deception — a private register that allowed me to feel honest while changing nothing in the public record. What I do instead, now, is read back a fraction more slowly when I sense the witness is one of those for whom the tidying might be doing too much work. I have no authority to refuse to tidy. The form of the transcript requires it. I do have a small authority — half a beat — over the pace at which the tidied version is offered, which gives the witness the chance to interrupt, and a few of them, perhaps a tenth, do.",
  "tags": ["Law", "Records", "Authorship"],
  "annotations": [
    { "phrase": "stenographer", "meaningVi": "thư ký tốc ký (toà án); người ghi lại lời nói trong phiên xử bằng máy tốc ký chuyên dụng", "pronunciation": "/stəˈnɒɡ.rə.fə/" },
    { "phrase": "stenographic camera", "meaningVi": "(ẩn dụ) chiếc máy quay tốc ký — hình dung sai về thư ký toà như công cụ thu trung lập" },
    { "phrase": "witness box", "meaningVi": "ô nhân chứng; nơi nhân chứng ngồi để làm chứng tại toà", "pronunciation": "/ˈwɪt.nəs bɒks/" },
    { "phrase": "act of authorship", "meaningVi": "hành vi sáng tạo/tác giả; ý nói thư ký toà không thuần thu mà còn quyết định", "pronunciation": "/ˈɔː.θə.ʃɪp/" },
    { "phrase": "phonemes", "meaningVi": "âm vị; đơn vị ngữ âm nhỏ nhất phân biệt nghĩa", "pronunciation": "/ˈfəʊ.niːmz/" },
    { "phrase": "supplying punctuation she did not hear", "meaningVi": "tự thêm dấu câu mà mình không nghe thấy — vì lời nói không có dấu chấm phẩy" },
    { "phrase": "breath marks", "meaningVi": "dấu hơi; các khoảng dừng ngắn trong lời nói — quyết định ranh giới câu", "pronunciation": "/breθ mɑːks/" },
    { "phrase": "counsel", "meaningVi": "luật sư biện hộ/cố vấn pháp lý (tại phiên toà)", "pronunciation": "/ˈkaʊn.səl/" },
    { "phrase": "ratifies", "meaningVi": "phê chuẩn; (ở đây) nhân chứng ngầm thông qua bản ghi bằng cách không phản đối", "pronunciation": "/ˈræt.ɪ.faɪz/" },
    { "phrase": "by the slender mechanism", "meaningVi": "bằng cơ chế mong manh; (ở đây) chỉ cần không cãi là đã đủ để 'thông qua'" },
    { "phrase": "parted company in small and binding ways", "meaningVi": "đã chia tay ở những điểm nhỏ nhưng có hiệu lực ràng buộc — ẩn dụ về sự rẽ đôi giữa lời nói và bản ghi" },
    { "phrase": "the read-back", "meaningVi": "việc đọc lại (lời khai); thao tác kỹ thuật đặc trưng trong toà án" },
    { "phrase": "consequential", "meaningVi": "có hậu quả; (ở đây) khoảnh khắc quyết định nhiều thứ về sau", "pronunciation": "/ˌkɒn.sɪˈkwen.ʃəl/" },
    { "phrase": "cool, ordered prose", "meaningVi": "văn xuôi mạch lạc, lạnh lùng; (ở đây) bản ghi đã được biên tập về dạng đọc được" },
    { "phrase": "honest mess of speech", "meaningVi": "mớ bòng bong thành thật của lời nói; sự lộn xộn vốn có của khẩu ngữ" },
    { "phrase": "tidier proxy", "meaningVi": "bản đại diện gọn gàng hơn; (ở đây) bản ghi đứng thay lời nói thật", "pronunciation": "/ˈtaɪ.di.ə ˈprɒk.si/" },
    { "phrase": "appeal court", "meaningVi": "toà phúc thẩm; cấp xét xử lại bản án — chỉ đọc bản ghi, không nghe nhân chứng" },
    { "phrase": "cross-examination", "meaningVi": "đối chất; thẩm vấn nhân chứng phía đối phương", "pronunciation": "/ˌkrɒs.ɪɡˌzæm.ɪˈneɪ.ʃən/" },
    { "phrase": "pressing for cleaner sentences", "meaningVi": "ép nhân chứng nói thành câu sạch hơn — kỹ thuật của luật sư khéo" },
    { "phrase": "self-deception", "meaningVi": "tự lừa dối bản thân", "pronunciation": "/ˌself.dɪˈsep.ʃən/" },
    { "phrase": "the public record", "meaningVi": "hồ sơ công; bản ghi chính thức của toà án, có giá trị pháp lý" },
    { "phrase": "half a beat", "meaningVi": "nửa nhịp; khoảng dừng cực ngắn — đơn vị thời gian rất nhỏ nhưng đủ để nhân chứng cắt ngang" },
    { "phrase": "departed materially", "meaningVi": "đi chệch một cách thực chất; (về bản ghi) khác lời khai theo cách không thể bỏ qua", "pronunciation": "/dɪˈpɑː.tɪd məˈtɪə.ri.ə.li/" },
    { "phrase": "tidying", "meaningVi": "việc dọn dẹp/làm gọn; (ở đây) hành vi biên tập câu lộn xộn thành câu trật tự", "pronunciation": "/ˈtaɪ.di.ɪŋ/" },
    { "phrase": "read aloud", "meaningVi": "đọc to lên — thời điểm quan trọng khi bản ghi trở thành văn bản được nhân chứng nghe và (ngầm) xác nhận", "pronunciation": "/riːd əˈlaʊd/" },
    { "phrase": "read back a fraction", "meaningVi": "đọc lại chậm hơn một chút — thủ thuật tinh tế mà người ghi âm dùng để cho nhân chứng cơ hội phản bác" },
    { "phrase": "three jurisdictions", "meaningVi": "ba thẩm quyền tư pháp — chỉ kinh nghiệm làm việc ở nhiều hệ thống pháp luật khác nhau, làm tăng thẩm quyền của người kể chuyện", "pronunciation": "/ˌdʒʊər.ɪsˈdɪk.ʃənz/" },
    { "phrase": "private log", "meaningVi": "sổ ghi chép riêng — tài liệu cá nhân không chính thức mà nhân vật giữ để theo dõi những trường hợp bản ghi chép lệch với lời khai" },
    { "phrase": "not contradicting", "meaningVi": "không phản bác — cơ chế thụ động mà qua đó nhân chứng xác nhận bản ghi; sự im lặng trở thành sự đồng ý pháp lý" },
    { "phrase": "in two languages", "meaningVi": "bằng hai ngôn ngữ — chi tiết chỉ phạm vi kinh nghiệm của nhân vật, làm sâu thêm tính phức tạp của quá trình ghi chép" }
  ],
  "grammarNotes": [
    {
      "title": "Hedging and controlled qualification at C1",
      "bodyVi": "Người viết C1 dùng các cụm rào (hedges) để giữ độ chính xác của tuyên bố — không nói quá, không bỏ qua khả năng sai. Trong bài: 'roughly two per cent', 'more often than not', 'perhaps a tenth', 'in my own judgement', 'in those instances'. Các cụm này không phải sự yếu đuối; chúng đặt khẳng định trong khung mà nó thực sự áp dụng. Đây là tín hiệu trí tuệ trưởng thành: khẳng định chỉ rộng đúng bằng bằng chứng cho phép.",
      "bodyEn": "C1 writers use hedges to calibrate the precision of a claim — neither overstating nor ignoring the possibility of error. From the passage: 'roughly two per cent', 'more often than not', 'perhaps a tenth', 'in my own judgement', 'in those instances'. These phrases are not weakness; they place a claim inside the frame in which it actually holds. It is a signal of intellectual maturity: a claim no broader than the evidence allows."
    }
  ],
  "translationVi": "Phần lớn mọi người hình dung thư ký tốc ký như một loại máy quay tốc ký — một người ghi lại điều được nói vì luật yêu cầu có bản ghi, và trung thành tỉ lệ với tốc độ của cô ấy. Đó là một sự hiểu sai, nhưng là một sự hiểu sai có ích. Nó là sự hiểu sai cho phép phiên xử tiếp tục. Cái thực sự diễn ra tại chiếc máy nhỏ cạnh ô nhân chứng gần với một hành vi sáng tác lặng lẽ, mà ít người trong phòng xử hiểu, và thư ký, nếu thành thật, sẽ không bảo vệ hoàn toàn.\n\nMáy ghi lại âm vị, không phải câu. Người tốc ký diễn dịch theo thời gian thực — gom các 'uh', tự thêm dấu câu cô không nghe được, quyết định câu hỏi kết thúc ở đâu và lời làm rõ bắt đầu ở đâu. Hai thư ký, làm việc từ cùng một bản âm thanh, sẽ tạo ra hai bản ghi khác nhau khoảng hai phần trăm nội dung; sự khác biệt gần như không bao giờ nằm ở chữ mà ở các dấu hơi giữa chúng, và dấu hơi quyết định nơi một câu thôi là một thứ và bắt đầu là thứ khác. Đây không phải là thất bại của nghề. Đây là nghề.\n\nKhoảnh khắc thú vị, tuy nhiên, không phải là việc ghi. Nó là việc đọc lại. Khi luật sư yêu cầu 'có thể đọc lại câu trả lời cuối của nhân chứng không', thứ được tạo ra không còn là bản ghi nữa. Nó là một văn bản. Và ngay khi văn bản đó được đọc thành tiếng trong tầm nghe của nhân chứng, một điều xảy ra mà không ai trong phòng thừa nhận đầy đủ: nhân chứng phê chuẩn nó. Cô gật đầu, hoặc cô sửa một từ, hoặc cô ngồi im, nhưng trong mỗi trường hợp bản ghi trở thành — bằng cơ chế mong manh là cô không phản đối — cái đã được nói. Việc đọc lại là hành vi khép câu hỏi. Sau đó, cái mà phòng xử nhớ không còn là lời khai nữa mà là bản ghi của lời khai, và đến lúc đó hai cái đã chia tay ở những điểm nhỏ nhưng ràng buộc.\n\nTôi đã đọc lại lời khai ba mươi mốt năm, trong ba khu vực tài phán, bằng hai ngôn ngữ. Điều tôi đã học, mà tôi sẽ không đoán trước được khi mới bắt đầu, là việc đọc lại là khoảnh khắc có hậu quả nhất của bất kỳ phiên xử nào ngoài bản án. Một nhân chứng được phép nghe lời mình vọng lại trong văn xuôi mạch lạc, lạnh lùng — dấu câu đã thêm, ngập ngừng đã được xếp gọn — sẽ, thường xuyên hơn không, an phận với phiên bản đó. Nó nghe giống cái cô muốn nói hơn cái cô thực sự nói. Mớ bòng bong thành thật của lời nói được thay thế, với sự đồng thuận của cô, bằng một bản đại diện gọn gàng hơn. Và bản đại diện ấy là cái toà phúc thẩm sẽ đọc, hai mươi tháng sau, trong một căn phòng cô sẽ không bao giờ thấy.\n\nCó những thư ký áy náy về điều này và những thư ký không. Tôi đã là cả hai vào các thời điểm khác nhau trong nghề. Phiên bản áy náy của tôi đã giữ một sổ ghi cá nhân, trong vài năm, về các khoảnh khắc mà việc đọc lại, theo phán đoán của riêng tôi, đi chệch lời khai một cách thực chất. Cuốn sổ ngắn. Nó chứa chưa đầy bốn mươi mục trong mười hai năm. Nhưng các mục có một mẫu hình: chúng gần như luôn liên quan đến nhân chứng mà tiếng Anh là ngôn ngữ thứ hai, nhân chứng đang khóc, nhân chứng bị đối chất bởi luật sư khéo ép thành câu sạch hơn năng lực của cô lúc đó. Việc đọc lại, trong những trường hợp đó, đã dọn dẹp họ. Họ chấp nhận sự dọn dẹp. Toà chấp nhận sự chấp nhận của họ.\n\nTôi không còn giữ sổ. Lý do không phải là tôi đã thôi nhận ra, mà tôi đến chỗ tin rằng cuốn sổ là sự tự lừa dối lặng lẽ của chính nó — một sổ ghi cá nhân cho phép tôi cảm thấy thành thật trong khi không thay đổi gì trong hồ sơ công. Cái tôi làm bây giờ, thay vào đó, là đọc lại chậm hơn một chút khi tôi cảm thấy nhân chứng thuộc nhóm mà sự dọn dẹp có thể đang làm việc quá mức. Tôi không có quyền từ chối việc dọn dẹp. Hình thức của bản ghi đòi hỏi. Tôi có một quyền nhỏ — nửa nhịp — về tốc độ mà phiên bản đã dọn được đưa ra, và điều đó cho nhân chứng cơ hội cắt ngang, và một vài người, có lẽ một phần mười, đã làm vậy.",
  "questions": [
    { "id": "q1", "prompt": "What is the popular misunderstanding about the stenographer, according to the writer?", "options": ["That she is illegally present", "That she is a stenographic camera — a person taking down what is said, faithful in proportion to her speed", "That she controls the verdict", "That she is a lawyer"], "answerIndex": 1, "explanation": "Her opening framing.", "hint": "Look at the opening sentence." },
    { "id": "q2", "prompt": "What does the writer say the stenographer is actually doing?", "options": ["Transcribing without judgement", "Carrying out a quiet act of authorship that few participants in a courtroom understand and which she herself, if honest, will not entirely defend", "Recording phonemes only", "Translating between languages"], "answerIndex": 1, "explanation": "Her contrast with the popular image.", "hint": "Look at the second half of paragraph one." },
    { "id": "q3", "prompt": "Where do two stenographers working from identical audio typically differ?", "options": ["In the choice of words", "In roughly two per cent of content, almost never in the words but in the breath marks between them — which decide where one sentence stops and another begins", "In the spelling", "In the punctuation of proper nouns only"], "answerIndex": 1, "explanation": "The technical claim of paragraph two.", "hint": "Look for the 'two per cent' figure." },
    { "id": "q4", "prompt": "What does the writer mean by 'This is not a failure of the profession. It is the profession.'?", "options": ["That stenographers are paid to fail", "That the interpretive work — collapsing 'uh's, supplying punctuation, choosing breath marks — is not a defect but the essence of what the stenographer does", "That the profession is dying", "That stenographers should be replaced by machines"], "answerIndex": 1, "explanation": "The aphorism of paragraph two.", "hint": "Read the final sentences of paragraph two together." },
    { "id": "q5", "prompt": "Which moment does the writer call the most interesting?", "options": ["The verdict", "Not the recording but the reading back of the transcript", "The opening statement", "The judge's instructions"], "answerIndex": 1, "explanation": "The opening of paragraph three.", "hint": "Look at the first sentence of paragraph three." },
    { "id": "q6", "prompt": "What happens during the read-back, according to the writer?", "options": ["Nothing of consequence", "The witness ratifies the transcript by not contradicting it — and the transcript becomes what was said", "The judge corrects the text", "The lawyer takes over"], "answerIndex": 1, "explanation": "Her central claim about the read-back.", "hint": "Look for the verb 'ratifies'." },
    { "id": "q7", "prompt": "What does the writer say happens to the room's memory after the read-back?", "options": ["Nothing changes", "What the room remembers is no longer the testimony but the transcript of the testimony — the two have parted company in small and binding ways", "The room forgets everything", "The room remembers only the verdict"], "answerIndex": 1, "explanation": "The close of paragraph three.", "hint": "Look at the last sentence of paragraph three." },
    { "id": "q8", "prompt": "What does the writer call the most consequential moment of any trial that is not the verdict?", "options": ["The cross-examination", "The read-back", "The opening statement", "The summing up"], "answerIndex": 1, "explanation": "Her central claim in paragraph four.", "hint": "Look for the phrase 'most consequential moment'." },
    { "id": "q9", "prompt": "Why does a witness typically settle for the tidier version of her testimony?", "options": ["Because she is forced to", "Because cool, ordered prose with supplied punctuation sounds more like what she meant than what she actually said", "Because she does not understand English", "Because she trusts the lawyer"], "answerIndex": 1, "explanation": "Her account of the settlement.", "hint": "Look at paragraph four for the phrase 'sounds more like what she meant'." },
    { "id": "q10", "prompt": "Who, in the writer's private log, was most often affected by the tidying?", "options": ["Police officers", "Witnesses for whom English was a second language, witnesses who had been crying, and witnesses under cross-examination by counsel skilled at pressing for cleaner sentences", "Defendants only", "Judges"], "answerIndex": 1, "explanation": "The three-fold pattern in the log.", "hint": "Look at paragraph five for the patterns." },
    { "id": "q11", "prompt": "How many entries did the log contain over twelve years?", "options": ["More than four hundred", "Fewer than forty", "Exactly one hundred", "None"], "answerIndex": 1, "explanation": "Stated directly.", "hint": "Look for the precise number in paragraph five." },
    { "id": "q12", "prompt": "Why did the writer stop keeping the log?", "options": ["Because she stopped noticing", "Because she came to believe the log was its own quiet self-deception — a private register that let her feel honest while changing nothing in the public record", "Because the court banned it", "Because she retired"], "answerIndex": 1, "explanation": "Her self-criticism in paragraph six.", "hint": "Look at the opening of paragraph six." },
    { "id": "q13", "prompt": "What does the writer do now instead of keeping the log?", "options": ["Refuses to tidy", "Reads back a fraction more slowly when she senses the witness is one for whom the tidying might be doing too much work — giving the witness, by half a beat, the chance to interrupt", "Reports to the judge", "Records on her phone"], "answerIndex": 1, "explanation": "Her current practice.", "hint": "Look at the closing of paragraph six." },
    { "id": "q14", "prompt": "Approximately what fraction of these witnesses, the writer estimates, do interrupt?", "options": ["A half", "A tenth (perhaps)", "A third", "None"], "answerIndex": 1, "explanation": "Stated as 'a few of them, perhaps a tenth, do'.", "hint": "Look at the final clause." },
    { "id": "q15", "prompt": "Which of these is the writer NOT claiming?", "options": ["That the stenographer's interpretive work is part of the profession, not a flaw in it.", "That the read-back is more consequential than the verdict.", "That witnesses often accept the tidier version as their own.", "That the appeal court reads the transcript, not the original testimony."], "answerIndex": 1, "explanation": "She explicitly hedges: 'the most consequential moment of any trial that is not the verdict'.", "hint": "Look at paragraph four for the qualifier." },
    { "id": "q16", "prompt": "Which paraphrase is closest to the writer's central position?", "options": ["The stenographer should be replaced by a recording device.", "The legal record is not what was said but a tidied proxy that the room agrees was what was said, and the moment of agreement is the read-back — a small authorship the witness ratifies without realising she is doing so.", "Witnesses always lie.", "Punctuation does not matter."], "answerIndex": 1, "explanation": "Her account threads through all paragraphs.", "hint": "Read paragraphs three and four together." }
  ],
  "cloze": {
    "template": "Most people imagine a stenographer as a kind of stenographic camera — a person taking down what is said because the law requires a record, and faithful in proportion to her speed. It is a misunderstanding, but a useful one. It is the misunderstanding that lets the room continue. What is in fact happening at the small machine by the witness box is closer to a quiet act of {{b1}}, one that few participants in a courtroom understand, and which the stenographer herself, if she is honest, will not entirely defend.\n\nThe machine records {{b2}}, not sentences. The reporter is interpreting in real time — collapsing 'uh's, supplying punctuation she did not hear, deciding where a question ends and a clarification begins. Two stenographers, working from identical audio, will produce transcripts that differ in roughly two per cent of their content; the differences are almost never in the words but in the {{b3}} marks between them, and breath marks decide where a sentence stops being one thing and starts being another. This is not a failure of the profession. It is the profession.\n\nThe interesting moment, however, is not the recording. It is the reading back. When counsel asks 'could you read back the witness's last answer', what is produced is no longer a recording at all. It is a text. And the moment that text is read aloud in the witness's hearing, something happens that nobody in the room quite acknowledges: the witness {{b4}} it. She nods, or she corrects a word, or she sits silent, but in each case the transcript becomes — by the slender {{b5}} of her not contradicting it — what was said. The reading back is the act that closes the question. After it, what the room remembers is no longer the testimony but the transcript of the testimony, and the two have, by then, parted {{b6}} in small and binding ways.\n\nI have read back testimony for thirty-one years, in three jurisdictions, in two languages. The thing I have learned, which I would not have predicted at the start, is that the read-back is the most {{b7}} moment of any trial that is not the verdict. A witness who is allowed to hear her words returned to her in cool, {{b8}} prose — punctuation supplied, hesitations filed away — will, more often than not, settle for that version. It sounds more like what she meant than what she actually said. The honest mess of speech is replaced, with her consent, by a {{b9}} proxy. And the tidier proxy is what the appeal court will read, twenty months later, in a room she will never see.\n\nThere are stenographers who are uneasy about this and stenographers who are not. I have been both at different points in my career. The uneasy version of me kept a private log, for several years, of moments where the read-back, in my own judgement, departed {{b10}} from the testimony. The log was short. It contained fewer than forty entries in twelve years. But the entries had a pattern: they almost always involved witnesses for whom English was a second language, witnesses who had been crying, witnesses under {{b11}} by counsel skilled at pressing for cleaner sentences than the witness was capable of. The read-back, in those instances, tidied them. They accepted the tidying. The court accepted their acceptance.\n\nI no longer keep the log. The reason is not that I have stopped noticing, but that I came to believe the log was its own quiet {{b12}} — a private register that allowed me to feel honest while changing nothing in the public record. What I do instead, now, is read back a fraction more slowly when I sense the witness is one of those for whom the tidying might be doing too much work. I have no authority to refuse to tidy. The form of the transcript requires it. I do have a small authority — half a {{b13}} — over the pace at which the {{b14}} version is offered, which gives the witness the chance to interrupt, and a few of them, perhaps a {{b15}}, do.",
    "blanks": [
      { "id": "b1", "options": ["authorship", "translation", "censorship", "memorisation"], "answerIndex": 0, "explanation": "A quiet act of authorship." },
      { "id": "b2", "options": ["phonemes", "sentences", "paragraphs", "vowels"], "answerIndex": 0, "explanation": "The machine records phonemes, not sentences." },
      { "id": "b3", "options": ["breath", "exclamation", "question", "stress"], "answerIndex": 0, "explanation": "The differences are in the breath marks." },
      { "id": "b4", "options": ["ratifies", "rejects", "translates", "deletes"], "answerIndex": 0, "explanation": "The witness ratifies it." },
      { "id": "b5", "options": ["mechanism", "celebration", "rumour", "argument"], "answerIndex": 0, "explanation": "By the slender mechanism of her not contradicting it." },
      { "id": "b6", "options": ["company", "ways", "favours", "doors"], "answerIndex": 0, "explanation": "The two have parted company in small and binding ways." },
      { "id": "b7", "options": ["consequential", "trivial", "celebrated", "secret"], "answerIndex": 0, "explanation": "The most consequential moment of any trial that is not the verdict." },
      { "id": "b8", "options": ["ordered", "broken", "passionate", "rhyming"], "answerIndex": 0, "explanation": "Cool, ordered prose." },
      { "id": "b9", "options": ["tidier", "louder", "shorter", "older"], "answerIndex": 0, "explanation": "A tidier proxy." },
      { "id": "b10", "options": ["materially", "musically", "barely", "amusingly"], "answerIndex": 0, "explanation": "Departed materially from the testimony." },
      { "id": "b11", "options": ["cross-examination", "celebration", "translation", "supervision"], "answerIndex": 0, "explanation": "Witnesses under cross-examination by counsel." },
      { "id": "b12", "options": ["self-deception", "celebration", "rebellion", "ceremony"], "answerIndex": 0, "explanation": "Its own quiet self-deception." },
      { "id": "b13", "options": ["beat", "page", "hour", "courtroom"], "answerIndex": 0, "explanation": "Half a beat over the pace." },
      { "id": "b14", "options": ["tidied", "broken", "musical", "secret"], "answerIndex": 0, "explanation": "The tidied version is offered." },
      { "id": "b15", "options": ["tenth", "half", "third", "quarter"], "answerIndex": 0, "explanation": "Perhaps a tenth do." }
    ]
  },
  "criticalThinkingQuestion": "The writer argues that the read-back is the moment at which a tidier proxy quietly displaces the witness's actual speech, with the witness's own consent. Think of an institutional record you have signed off on — a meeting minute, an interview summary, a customer-complaint transcript, a translated quote attributed to you. Did you correct it? Did you settle for it? And, on reflection, did the tidied version sound more like what you meant than what you actually said — and is that an improvement or a small, binding loss?"
}
